ballpackage_ubiloctech/Background.py
ballpackage_ubiloctech/BouncingBall.py
ballpackage_ubiloctech/CustomExceptions.py
ballpackage_ubiloctech/InelasticBouncingBall-main.py
ballpackage_ubiloctech/Vector.py
ballpackage_ubiloctech/__init__.py
ballpackage_ubiloctech/mathcorrections.py
ballpackage_ubiloctech-0.0.1.dist-info/LICENSE
ballpackage_ubiloctech-0.0.1.dist-info/METADATA
ballpackage_ubiloctech-0.0.1.dist-info/WHEEL
ballpackage_ubiloctech-0.0.1.dist-info/top_level.txt
ballpackage_ubiloctech-0.0.1.dist-info/RECORD
